{"skeleton":{"hash":"+J2P2yL8IfpBQZXSB6q+xXzsytc","spine":"3.8.75","x":-251,"y":-251,"width":502,"height":502,"images":"F:/gun/1/images/images/","audio":"F:/gun/1/images"},"bones":[{"name":"root"},{"name":"bone","parent":"root","x":-0.05,"y":-0.01}],"slots":[{"name":"spr_focus_arrow_0","bone":"bone","attachment":"spr_focus_arrow_0"},{"name":"b41 (1)","bone":"root","attachment":"b41-(1)"}],"skins":[{"name":"default","attachments":{"spr_focus_arrow_0":{"spr_focus_arrow_0":{"color":"a869c0ff","x":0.05,"y":0.01,"width":502,"height":502}},"b41 (1)":{"b41-(1)":{"width":364,"height":360},"b41-(2)":{"width":362,"height":358},"b41-(3)":{"x":0.5,"width":335,"height":360},"b41-(4)":{"width":334,"height":346},"b41-(5)":{"x":0.5,"width":345,"height":364},"b41-(6)":{"x":0.5,"width":347,"height":360},"b41-(7)":{"x":0.5,"width":359,"height":360},"b41-(8)":{"x":0.5,"width":359,"height":360},"b41-(9)":{"y":0.5,"width":360,"height":357},"b41-(10)":{"width":360,"height":352},"b41-(11)":{"y":0.5,"width":362,"height":359},"b41-(12)":{"y":0.5,"width":384,"height":399},"b41-(13)":{"y":0.5,"width":382,"height":399},"b41-(14)":{"width":382,"height":404},"b41-(15)":{"width":384,"height":404}}}}],"animations":{"attack":{"slots":{"b41 (1)":{"attachment":[{"name":"b41-(8)"},{"time":0.1667,"name":"b41-(9)"},{"time":0.3333,"name":"b41-(10)"},{"time":0.5,"name":"b41-(11)"},{"time":0.6667,"name":"b41-(12)"},{"time":0.8333,"name":"b41-(13)"},{"time":1,"name":"b41-(14)"},{"time":1.1667,"name":"b41-(15)"}]}},"bones":{"bone":{"rotate":[{},{"time":1,"angle":180},{"time":1.3333,"angle":120}]}}},"die":{"slots":{"b41 (1)":{"attachment":[{"name":"b41-(7)"}]}},"bones":{"root":{"rotate":[{},{"time":0.1667,"angle":180},{"time":0.3333},{"time":0.5,"angle":180},{"time":0.6667},{"time":0.8333,"angle":180},{"time":1}]}}},"hurt":{"slots":{"b41 (1)":{"attachment":[{"name":"b41-(7)"}]}},"bones":{"root":{"translate":[{},{"time":0.1667,"x":-30}]},"bone":{"rotate":[{},{"time":0.1667,"angle":-30}]}}},"idle_loop":{"slots":{"b41 (1)":{"attachment":[{"name":"b41-(8)"},{"time":0.1667,"name":"b41-(9)"},{"time":0.3333,"name":"b41-(10)"},{"time":0.5,"name":"b41-(11)"},{"time":0.6667,"name":"b41-(8)"},{"time":0.8333,"name":"b41-(9)"},{"time":1,"name":"b41-(10)"},{"time":1.1667,"name":"b41-(11)"},{"time":1.3333,"name":"b41-(8)"},{"time":1.5,"name":"b41-(9)"},{"time":1.6667,"name":"b41-(10)"},{"time":1.8333,"name":"b41-(11)"},{"time":2,"name":"b41-(8)"}]}},"bones":{"bone":{"rotate":[{},{"time":1,"angle":180},{"time":2}]}}},"power":{"slots":{"b41 (1)":{"attachment":[{"name":"b41-(8)"},{"time":0.1667,"name":"b41-(9)"},{"time":0.3333,"name":"b41-(10)"},{"time":0.5,"name":"b41-(11)"},{"time":0.6667,"name":"b41-(8)"},{"time":0.8333,"name":"b41-(9)"},{"time":1,"name":"b41-(10)"},{"time":1.1667,"name":"b41-(11)"},{"time":1.3333,"name":"b41-(8)"},{"time":1.5,"name":"b41-(9)"},{"time":1.6667,"name":"b41-(10)"},{"time":1.8333,"name":"b41-(11)"},{"time":2,"name":"b41-(8)"}]}},"bones":{"bone":{"rotate":[{},{"time":1,"angle":180},{"time":2}],"scale":[{"time":0.6667},{"time":1,"x":2,"y":2},{"time":1.3333}]}}}}}